hamel/__init__.py
hamel/_modidx.py
hamel/annotate_talk_cli.py
hamel/chapters_cli.py
hamel/gem.py
hamel/gem_cli.py
hamel/kit_cli.py
hamel/transcribe_cli.py
hamel/writing.py
hamel/yt.py
hamel/zoom.py
hamel/zoom_cli.py
hamel-0.0.28.dist-info/licenses/LICENSE
hamel-0.0.28.dist-info/METADATA
hamel-0.0.28.dist-info/WHEEL
hamel-0.0.28.dist-info/entry_points.txt
hamel-0.0.28.dist-info/top_level.txt
hamel-0.0.28.dist-info/RECORD
