Metadata-Version: 2.4
Name: hamel
Version: 0.0.28
Summary: General Utilities
Home-page: https://github.com/hamelsmu/hamel
Author: Hamel Husain
Author-email: hamel.husain@gmail.com
License: Apache Software License 2.0
Keywords: nbdev jupyter notebook python
Classifier: Development Status :: 4 - Beta
Classifier: Intended Audience :: Developers
Classifier: Natural Language :: English
Classifier: Programming Language :: Python :: 3.9
Classifier: Programming Language :: Python :: 3.10
Classifier: Programming Language :: Python :: 3.11
Classifier: Programming Language :: Python :: 3.12
Classifier: License :: OSI Approved :: Apache Software License
Requires-Python: >=3.9
License-File: LICENSE
Requires-Dist: typer
Requires-Dist: youtube_transcript_api
Requires-Dist: httpx
Requires-Dist: fastcore
Requires-Dist: google-genai
Requires-Dist: openai-whisper
Requires-Dist: fastprogress
Requires-Dist: python-dotenv
Requires-Dist: rich
Requires-Dist: ipython
Requires-Dist: typing_extensions
Provides-Extra: dev
Dynamic: author
Dynamic: author-email
Dynamic: classifier
Dynamic: description
Dynamic: description-content-type
Dynamic: home-page
Dynamic: keywords
Dynamic: license
Dynamic: license-file
Dynamic: provides-extra
Dynamic: requires-dist
Dynamic: requires-python
Dynamic: summary
